alice/VERSION
alice/__init__.py
alice/config.py
alice/public_api.py
alice/auth/__init__.py
alice/auth/auth.py
alice/auth/auth_client.py
alice/auth/auth_errors.py
alice/auth/cached_token_stack.py
alice/auth/token_tools.py
alice/face/__init__.py
alice/face/face.py
alice/face/face_models.py
alice/onboarding/__init__.py
alice/onboarding/onboarding.py
alice/onboarding/onboarding_client.py
alice/onboarding/onboarding_errors.py
alice/onboarding/tools.py
alice/onboarding/enums/__init__.py
alice/onboarding/enums/certificate_locale.py
alice/onboarding/enums/decision.py
alice/onboarding/enums/document_side.py
alice/onboarding/enums/document_source.py
alice/onboarding/enums/document_type.py
alice/onboarding/enums/environment.py
alice/onboarding/enums/match_case.py
alice/onboarding/enums/onboarding_steps.py
alice/onboarding/enums/user_state.py
alice/onboarding/enums/version.py
alice/onboarding/models/__init__.py
alice/onboarding/models/bounding_box.py
alice/onboarding/models/device_info.py
alice/onboarding/models/request_runner.py
alice/onboarding/models/user_info.py
alice/onboarding/models/report/__init__.py
alice/onboarding/models/report/report.py
alice/onboarding/models/report/checks/__init__.py
alice/onboarding/models/report/checks/check.py
alice/onboarding/models/report/checks/document/__init__.py
alice/onboarding/models/report/checks/document/authentic_nfc_chip_check.py
alice/onboarding/models/report/checks/document/checked_info_code_check.py
alice/onboarding/models/report/checks/document/coherent_document_dates_check.py
alice/onboarding/models/report/checks/document/consistent_document_check.py
alice/onboarding/models/report/checks/document/expected_document_check.py
alice/onboarding/models/report/checks/document/face_in_document_check.py
alice/onboarding/models/report/checks/document/face_matching_document_check.py
alice/onboarding/models/report/checks/document/not_a_printed_document_check.py
alice/onboarding/models/report/checks/document/not_a_screen_document_check.py
alice_onboarding-5.1.2.dist-info/LICENSE
alice_onboarding-5.1.2.dist-info/METADATA
alice_onboarding-5.1.2.dist-info/WHEEL
alice_onboarding-5.1.2.dist-info/top_level.txt
alice_onboarding-5.1.2.dist-info/RECORD
