Metadata-Version: 2.1
Name: alice-onboarding
Version: 5.1.2
Summary: Alice Onboarding Python SDK
Home-page: https://github.com/alice-biometrics/onboarding-python
Author: Alice Biometrics
Author-email: support@alicebiometrics.com
License: Alice Copyright
Keywords: onboarding,biometrics,kyc,alice
Classifier: License :: OSI Approved :: MIT License
Classifier: Programming Language :: Python
Classifier: Programming Language :: Python :: 3
Classifier: Programming Language :: Python :: 3 :: Only
Classifier: Programming Language :: Python :: 3.7
Classifier: Programming Language :: Python :: 3.8
Classifier: Programming Language :: Python :: 3.9
Classifier: Programming Language :: Python :: 3.10
Classifier: Programming Language :: Python :: 3.11
Classifier: Programming Language :: Python :: 3.12
License-File: LICENSE
Requires-Dist: pyjwt<3,>=2.3.0
Requires-Dist: pydantic<3,>=1.8.2
Requires-Dist: pydantic-settings<3
Requires-Dist: requests<3,>=2.26.0
Requires-Dist: meiga<2,>=1.9.1
Requires-Dist: requests-toolbelt<2
